tkreload/__init__.py
tkreload/app_event_handler.py
tkreload/auto_reload.py
tkreload/file_utils.py
tkreload/help.py
tkreload/main.py
tkreload/progress.py
tkreload-1.0.3.dist-info/LICENSE
tkreload-1.0.3.dist-info/METADATA
tkreload-1.0.3.dist-info/WHEEL
tkreload-1.0.3.dist-info/entry_points.txt
tkreload-1.0.3.dist-info/top_level.txt
tkreload-1.0.3.dist-info/RECORD
