Metadata-Version: 2.1
Name: tkreload
Version: 1.0.3
Summary: A library that auto reloads your tkinter app whenever file changes are detected.
Author-email: iamDyeus <dyeusyt@gmail.com>
License: Apache License 2.0
Project-URL: Documentation, https://github.com/iamDyeus/tkreload/blob/main/README.md
Project-URL: Bug Tracker, https://github.com/iamDyeus/tkreload/issues
Project-URL: Source code, https://github.com/iamDyeus/tkreload
Classifier: Development Status :: 5 - Production/Stable
Classifier: Intended Audience :: Developers
Classifier: Topic :: Software Development :: Build Tools
Classifier: License :: OSI Approved :: Apache Software License
Classifier: Programming Language :: Python :: 3
Requires-Python: >=3.9
License-File: LICENSE
Requires-Dist: watchdog >=5.0.3
Requires-Dist: rich >=13.9.2
Provides-Extra: test
Requires-Dist: pytest >=7 ; extra == 'test'
Requires-Dist: pytest-cov ; extra == 'test'
